wireguard_manager/__init__.py
wireguard_manager/config.py
wireguard_manager/exceptions.py
wireguard_manager/interface.py
wireguard_manager/manager.py
wireguard_manager/peer.py
wireguard_manager/utils.py
wireguard_manager-0.0.2.2.dist-info/LICENSE
wireguard_manager-0.0.2.2.dist-info/METADATA
wireguard_manager-0.0.2.2.dist-info/WHEEL
wireguard_manager-0.0.2.2.dist-info/top_level.txt
wireguard_manager-0.0.2.2.dist-info/RECORD
