Metadata-Version: 2.1
Name: wireguard-manager
Version: 0.0.2.2
Summary: Wireguard management tool
Author: Egor Kardasov
Author-email: <egor@kardasov.ru>
Keywords: python,vpn,wireguard,server,manager
Classifier: Development Status :: 2 - Pre-Alpha
Classifier: Intended Audience :: Developers
Classifier: Programming Language :: Python :: 3
Classifier: Operating System :: Unix
Classifier: Operating System :: MacOS :: MacOS X
Classifier: Operating System :: Microsoft :: Windows
License-File: LICENSE
Requires-Dist: cryptography
